physic/__init__.py
physic/main.py
Physic-1.2.dist-info/LICENSE.txt
Physic-1.2.dist-info/METADATA
Physic-1.2.dist-info/WHEEL
Physic-1.2.dist-info/top_level.txt
Physic-1.2.dist-info/RECORD
